odoo10_addon_stock_account_change_product_valuation-10.0.1.0.0-py2.7-nspkg.pth
odoo/addons/stock_account_change_product_valuation/README.rst
odoo/addons/stock_account_change_product_valuation/__init__.py
odoo/addons/stock_account_change_product_valuation/__manifest__.py
odoo/addons/stock_account_change_product_valuation/i18n/ca.po
odoo/addons/stock_account_change_product_valuation/i18n/de.po
odoo/addons/stock_account_change_product_valuation/i18n/es.po
odoo/addons/stock_account_change_product_valuation/i18n/es_MX.po
odoo/addons/stock_account_change_product_valuation/i18n/fi.po
odoo/addons/stock_account_change_product_valuation/i18n/fr.po
odoo/addons/stock_account_change_product_valuation/i18n/fr_CH.po
odoo/addons/stock_account_change_product_valuation/i18n/hr.po
odoo/addons/stock_account_change_product_valuation/i18n/hr_HR.po
odoo/addons/stock_account_change_product_valuation/i18n/it.po
odoo/addons/stock_account_change_product_valuation/i18n/pt_BR.po
odoo/addons/stock_account_change_product_valuation/i18n/ro.po
odoo/addons/stock_account_change_product_valuation/i18n/sl.po
odoo/addons/stock_account_change_product_valuation/i18n/tr_TR.po
odoo/addons/stock_account_change_product_valuation/i18n/vi_VN.po
odoo/addons/stock_account_change_product_valuation/i18n/zh_CN.po
odoo/addons/stock_account_change_product_valuation/models/__init__.py
odoo/addons/stock_account_change_product_valuation/models/product.py
odoo/addons/stock_account_change_product_valuation/models/product_category.py
odoo/addons/stock_account_change_product_valuation/static/description/icon.png
odoo/addons/stock_account_change_product_valuation/tests/__init__.py
odoo/addons/stock_account_change_product_valuation/tests/test_stock_account_product_change_product_type.py
odoo10_addon_stock_account_change_product_valuation-10.0.1.0.0.dist-info/DESCRIPTION.rst
odoo10_addon_stock_account_change_product_valuation-10.0.1.0.0.dist-info/METADATA
odoo10_addon_stock_account_change_product_valuation-10.0.1.0.0.dist-info/RECORD
odoo10_addon_stock_account_change_product_valuation-10.0.1.0.0.dist-info/WHEEL
odoo10_addon_stock_account_change_product_valuation-10.0.1.0.0.dist-info/metadata.json
odoo10_addon_stock_account_change_product_valuation-10.0.1.0.0.dist-info/namespace_packages.txt
odoo10_addon_stock_account_change_product_valuation-10.0.1.0.0.dist-info/top_level.txt
