Metadata-Version: 2.0
Name: odoo10-addon-stock-account-change-product-valuation
Version: 10.0.1.0.0
Summary: Adjusts valuation of the products and quants when the cost method or type of a product changes
Home-page: https://github.com/OCA/stock-logistics-warehouse
Author: Eficent Business and IT Consulting Services S.L., Odoo Community Association (OCA)
Author-email: support@odoo-community.org
License: AGPL-3
Platform: UNKNOWN
Classifier: Programming Language :: Python
Classifier: Framework :: Odoo
Classifier: License :: OSI Approved :: GNU Affero General Public License v3
Requires-Python: ~=2.7
Requires-Dist: odoo (<10.1dev,>=10.0)
